{
  "seaf.ia.logical_attributes": {
    "flix.content.film.description": {
      "code": "description",
      "title": "Краткое описание",
      "description": "text.None",
      "logical_entity": "flix.content.film",
      "link_attr": null
    },
    "flix.content.film.category": {
      "code": "category",
      "title": "категория",
      "description": "smallint.['PRIMARY KEY', 'FOREIGN KEY']",
      "logical_entity": "flix.content.film",
      "business_term": "flix.content.category",
      "link_attr": "flix.content.category"
    },
    "flix.content.film.actors": {
      "code": "actor",
      "title": "актеры",
      "description": "smallint.['FOREIGN KEY', 'PRIMARY KEY']",
      "logical_entity": "flix.content.film",
      "business_term": "flix.content.actor",
      "link_attr": "flix.content.actor",
      "link_type": "аггрегация"
    },
    "flix.content.film.actresses": {
      "code": "actor",
      "title": "актрисы",
      "description": "smallint.['FOREIGN KEY', 'PRIMARY KEY']",
      "logical_entity": "flix.content.film",
      "business_term": "flix.content.actor",
      "link_attr": "flix.content.actress",
      "link_type": "аггрегация"
    },
    "flix.content.film.release_year": {
      "code": "release_year",
      "title": "год выпуска",
      "description": "integer.None",
      "logical_entity": "flix.content.film",
      "link_attr": null
    },
    "flix.content.film.language": {
      "code": "language",
      "title": "язык",
      "description": "smallint.['FOREIGN KEY']",
      "logical_entity": "flix.content.film",
      "business_term": "flix.content.language",
      "link_attr": "flix.content.language"
    },
    "flix.content.film.rental_duration": {
      "code": "rental_duration",
      "title": "длительность проката",
      "description": "smallint.None",
      "logical_entity": "flix.content.film",
      "link_attr": null
    },
    "flix.content.film.length": {
      "code": "length",
      "title": "продолжительность фильма",
      "description": "smallint.None",
      "logical_entity": "flix.content.film",
      "link_attr": null
    },
    "flix.content.film.rating": {
      "code": "rating",
      "title": "рэйтинг",
      "description": "USER-DEFINED.None",
      "logical_entity": "flix.content.film",
      "business_term": "flix.recom.rating",
      "link_attr": null
    },

    "flix.content.actor.first_name": {
      "code": "first_name",
      "title": "Имя",
      "description": "character varying.None",
      "logical_entity": "flix.content.actor",
      "link_attr": null
    },
    "flix.content.actor.last_name": {
      "code": "last_name",
      "title": "Фамилия",
      "description": "character varying.None",
      "logical_entity": "flix.content.actor",
      "link_attr": null
    },
    "flix.content.actor.films": {
      "code": "films",
      "title": "фильмы",
      "description": "character varying.None",
      "logical_entity": "flix.content.actor",
      "business_term": "flix.content.film",
      "link_attr": "flix.content.film",
      "link_type": "аггрегация"
    },
    
    "flix.content.actress.first_name": {
      "code": "first_name",
      "title": "Имя",
      "description": "character varying.None",
      "logical_entity": "flix.content.actress",
      "link_attr": null
    },
    "flix.content.actress.last_name": {
      "code": "last_name",
      "title": "Фамилия",
      "description": "character varying.None",
      "logical_entity": "flix.content.actress",
      "link_attr": null
    },
    "flix.content.actress.films": {
      "code": "films",
      "title": "фильмы",
      "description": "character varying.None",
      "logical_entity": "flix.content.actress",
      "business_term": "flix.content.film",
      "link_attr": "flix.content.film",
      "link_type": "аггрегация"
    },
    
    "flix.address.district": {
      "code": "district",
      "title": "район",
      "description": "character varying.None",
      "logical_entity": "flix.address",
      "link_attr": null
    },
    "flix.address.city": {
      "code": "city",
      "title": "город",
      "description": "smallint.['FOREIGN KEY']",
      "logical_entity": "flix.address",
      "link_attr": "flix.city"
    },
    "flix.address.postal_code": {
      "code": "postal_code",
      "title": "почтовый индекс",
      "description": "character varying.None",
      "logical_entity": "flix.address",
      "business_term": "flix.postal_code",
      "link_attr": null
    },
    "flix.address.phone": {
      "code": "phone",
      "title": "телефон",
      "description": "character varying.None",
      "logical_entity": "flix.address",
      "business_term": "flix.phone",
      "link_attr": null
    },
    "flix.addressFL.parent": {
      "code": "parent",
      "title": "Родительский класс",
      "description": "character varying.None",
      "logical_entity": "flix.addressFL",
      "business_term": "flix.address",
      "link_attr": "flix.address",
      "link_type": "обобщение"
    },
    "flix.addressUL.parent": {
      "code": "parent",
      "title": "Родительский класс",
      "description": "character varying.None",
      "logical_entity": "flix.addressUL",
      "business_term": "flix.address",
      "link_attr": "flix.address",
      "link_type": "обобщение"
    },
    "flix.city.country": {
      "code": "country",
      "title": "страна",
      "description": "smallint.['FOREIGN KEY']",
      "logical_entity": "flix.city",
      "business_term": "flix.country",
      "link_attr": "flix.country",
      "link_type": "зависимость"
    },

    "flix.staff.first_name": {
      "code": "first_name",
      "title": "имя",
      "description": "character varying.None",
      "logical_entity": "flix.staff",
      "link_attr": null
    },
    "flix.staff.last_name": {
      "code": "last_name",
      "title": "фамилия",
      "description": "character varying.None",
      "logical_entity": "flix.staff",
      "link_attr": null
    },
    "flix.staff.address": {
      "code": "address",
      "title": "адрес",
      "description": "smallint.['FOREIGN KEY']",
      "logical_entity": "flix.staff",
      "business_term": "flix.address",
      "link_attr": "flix.addressUL"
    },
    "flix.staff.email": {
      "code": "email",
      "title": "email сотрудника",
      "description": "character varying.None",
      "logical_entity": "flix.staff",
      "link_attr": null
    },

    "alfa.fl.customer.first_name": {
      "code": "first_name",
      "title": "Имя",
      "description": "character varying.None",
      "logical_entity": "alfa.fl.customer",
      "link_attr": null
    },
    "alfa.fl.customer.last_name": {
      "code": "last_name",
      "title": "Фамилия",
      "description": "character varying.None",
      "logical_entity": "alfa.fl.customer",
      "link_attr": null
    },
    "alfa.fl.customer.email": {
      "code": "email",
      "title": "email",
      "description": "character varying.None",
      "logical_entity": "alfa.fl.customer",
      "link_attr": null
    },
    "alfa.fl.customer.address": {
      "code": "address",
      "title": "адрес",
      "description": "smallint.['FOREIGN KEY']",
      "logical_entity": "alfa.fl.customer",
      "business_term": "flix.address",
      "link_attr": "flix.address"
    },
    "alfa.fl.payment.customer": {
      "code": "customer",
      "title": "покупатель",
      "description": "smallint.['FOREIGN KEY']",
      "logical_entity": "alfa.fl.payment",
      "link_attr": "alfa.fl.customer"
    },
    "alfa.fl.payment.staff": {
      "code": "staff_id",
      "title": "менеджер продаж",
      "description": "smallint.['FOREIGN KEY']",
      "logical_entity": "alfa.fl.payment",
      "business_term": "flix.staff",
      "link_attr": "flix.staff"
    },
    "alfa.fl.payment.rental": {
      "code": "rental",
      "title": "договор оплаты",
      "description": "integer.['FOREIGN KEY']",
      "logical_entity": "alfa.fl.payment",
      "business_term": "rental_id",
      "link_attr": "rental"
    },
    "alfa.fl.payment.amount": {
      "code": "amount",
      "title": "стоимость",
      "description": "numeric.None",
      "logical_entity": "alfa.fl.payment",
      "link_attr": null
    },
    "alfa.fl.payment.payment_date": {
      "code": "payment_date",
      "title": "дата оплаты",
      "description": "timestamp without time zone.None",
      "logical_entity": "alfa.fl.payment",
      "link_attr": null
    }
  }
}